robstride/__init__.py
robstride/cli.py
robstride/client.py
robstride-0.1.0.dist-info/LICENSE
robstride-0.1.0.dist-info/METADATA
robstride-0.1.0.dist-info/WHEEL
robstride-0.1.0.dist-info/entry_points.txt
robstride-0.1.0.dist-info/top_level.txt
robstride-0.1.0.dist-info/RECORD
